{
	"id": "JdjRJLppX29viOB",
	"json": "{\"id\":\"JdjRJLppX29viOB\",\"url\":\"https://linktr.ee/rbxsamurai\",\"loadedUrl\":\"https://linktr.ee/rbxsamurai\",\"uniqueKey\":\"https://linktr.ee/rbxsamurai\",\"method\":\"GET\",\"noRetry\":false,\"retryCount\":0,\"errorMessages\":[],\"headers\":{},\"userData\":{\"label\":\"detail\",\"__crawlee\":{\"state\":4}},\"handledAt\":\"2022-12-27T04:42:43.402Z\"}",
	"method": "GET",
	"orderNo": null,
	"retryCount": 0,
	"uniqueKey": "https://linktr.ee/rbxsamurai",
	"url": "https://linktr.ee/rbxsamurai"
}