{
	"id": "v1e58yqQE32k7a0",
	"json": "{\"id\":\"v1e58yqQE32k7a0\",\"url\":\"https://linktr.ee/designeatrepeat\",\"loadedUrl\":\"https://linktr.ee/designeatrepeat\",\"uniqueKey\":\"https://linktr.ee/designeatrepeat\",\"method\":\"GET\",\"noRetry\":false,\"retryCount\":0,\"errorMessages\":[],\"headers\":{},\"userData\":{\"label\":\"detail\",\"__crawlee\":{\"state\":4}},\"handledAt\":\"2022-12-27T04:53:43.424Z\"}",
	"method": "GET",
	"orderNo": null,
	"retryCount": 0,
	"uniqueKey": "https://linktr.ee/designeatrepeat",
	"url": "https://linktr.ee/designeatrepeat"
}