{
	"id": "ylR1kg7R8zAJSJt",
	"json": "{\"id\":\"ylR1kg7R8zAJSJt\",\"url\":\"https://linktr.ee/ariagloves\",\"loadedUrl\":\"https://linktr.ee/ariagloves\",\"uniqueKey\":\"https://linktr.ee/ariagloves\",\"method\":\"GET\",\"noRetry\":false,\"retryCount\":0,\"errorMessages\":[],\"headers\":{},\"userData\":{\"label\":\"detail\",\"__crawlee\":{\"state\":4}},\"handledAt\":\"2022-12-27T04:42:42.689Z\"}",
	"method": "GET",
	"orderNo": null,
	"retryCount": 0,
	"uniqueKey": "https://linktr.ee/ariagloves",
	"url": "https://linktr.ee/ariagloves"
}